[
  {
    "Name": "device-id",
    "Value": "3f4cdd2f-66d9-4296-b867-5eff57ae6af8aaa",
    "Path": "/",
    "Domain": "coupang.com",
    "Secure": false,
    "Expires": "0001-01-01T00:00:00"
  },
  {
    "Name": "version",
    "Value": "1.8.4",
    "Path": "/",
    "Domain": "coupang.com",
    "Secure": false,
    "Expires": "0001-01-01T00:00:00"
  },
  {
    "Name": "app-type",
    "Value": "COUPANG_POS",
    "Path": "/",
    "Domain": "coupang.com",
    "Secure": false,
    "Expires": "0001-01-01T00:00:00"
  },
  {
    "Name": "access-token",
    "Value": "d96facbf43e4d2052e30842a16ab85dac0c5f4538a9000332fff1284f601055a",
    "Path": "/",
    "Domain": "coupang.com",
    "Secure": true,
    "Expires": "2024-04-12T16:24:54.9265302+08:00"
  },
  {
    "Name": "refresh-token",
    "Value": "06ab64bd35d28c3d5407cea4d27e5b44f8cb14e9d85292704f6f8cbeb6470d69",
    "Path": "/",
    "Domain": "coupang.com",
    "Secure": true,
    "Expires": "2024-04-12T16:24:54.9265302+08:00"
  },
  {
    "Name": "account-id",
    "Value": "89219",
    "Path": "/",
    "Domain": "coupang.com",
    "Secure": true,
    "Expires": "2024-04-12T16:24:54.9265302+08:00"
  },
  {
    "Name": "store-id",
    "Value": "192569",
    "Path": "/",
    "Domain": "coupang.com",
    "Secure": true,
    "Expires": "2024-04-12T16:24:56.4663809+08:00"
  },
  {
    "Name": "integrated-store-ids",
    "Value": "",
    "Path": "/",
    "Domain": "coupang.com",
    "Secure": true,
    "Expires": "2024-04-12T16:24:56.4663809+08:00"
  },
  {
    "Name": "SESSION",
    "Value": "YzNmYmY2OTktYzYwYi00ZjllLWIwZDEtOWY4ODBkY2I5NWRk",
    "Path": "/",
    "Domain": "coupang.com",
    "Secure": true,
    "Expires": "0001-01-01T00:00:00"
  }
]